remove_directory/__init__.py
remove_directory/version.py
remove_directory-0.0.1.dist-info/LICENSE
remove_directory-0.0.1.dist-info/METADATA
remove_directory-0.0.1.dist-info/WHEEL
remove_directory-0.0.1.dist-info/top_level.txt
remove_directory-0.0.1.dist-info/RECORD
