Metadata-Version: 2.1
Name: remove-directory
Version: 0.0.1
Summary: Recursively removes a non-empty directory
Home-page: https://github.com/Nagidal/remove_directory
Author: Борис Верховский
Author-email: sven.siegmund@gmail.com
License: UNKNOWN
Keywords: rmdir,remove dir,remove directory,recursive
Platform: any
Classifier: Development Status :: 5 - Production/Stable
Classifier: Intended Audience :: End Users/Desktop
Classifier: Intended Audience :: Developers
Classifier: Intended Audience :: System Administrators
Classifier: Environment :: Console
Classifier: Topic :: Software Development :: Testing
Classifier: License :: OSI Approved :: MIT License
Classifier: Natural Language :: English
Classifier: Programming Language :: Python :: 3.9
Classifier: Operating System :: OS Independent
Classifier: Operating System :: Microsoft :: Windows
Classifier: Operating System :: POSIX :: Linux
Classifier: Operating System :: MacOS :: MacOS X
Requires-Python: >=3.9
License-File: LICENSE
